cenas/__init__.py
cenas/admin.py
cenas/apps.py
cenas/models.py
cenas/tests.py
cenas/urls.py
cenas/views.py
cenas/migrations/__init__.py
cenas/templates/home.html
cenas/templates/upload_form.html
cenas1/__init__.py
cenas1/asgi.py
cenas1/settings.py
cenas1/urls.py
cenas1/wsgi.py
cenas-1.1.50.dist-info/METADATA
cenas-1.1.50.dist-info/WHEEL
cenas-1.1.50.dist-info/entry_points.txt
cenas-1.1.50.dist-info/top_level.txt
cenas-1.1.50.dist-info/RECORD
