Metadata-Version: 2.1
Name: cenas
Version: 1.1.50
Requires-Dist: django
